{
    "$schema": "menu_schema.json",
    "data": {
        "menuList": [{
                "url": "main.RechargePay",
                "src": "imgs/tab_loan/menu/ic_laon__dkjsq.png",
                "name": "贷款计算器"
            },
            {
                "url": "main.RechargeWater",
                "src": "imgs/tab_loan/menu/ic_laon__wydk.png",
                "name": "我要贷款"
            },
            {
                "url": "main.RechargeGas",
                "src": "imgs/tab_loan/menu/ic_laon__sqjd.png",
                "name": "申请进度"
            },
            {
                "url": "main.RechargePhone",
                "src": "imgs/tab_loan/menu/ic_laon__wddk.png",
                "name": "我的贷款"
            }
           
        ],
        "columns": 4
        
    }
}